RESSPyLab/RESSPyLab.py
RESSPyLab/__init__.py
RESSPyLab/auglag_factory.py
RESSPyLab/auglag_gen_solver.py
RESSPyLab/barrier_function.py
RESSPyLab/basic_dumper.py
RESSPyLab/cli.py
RESSPyLab/data_readers.py
RESSPyLab/eq_from_ineq_constraint.py
RESSPyLab/gensolver_dumper.py
RESSPyLab/log_barrier.py
RESSPyLab/mat_model_error_nda.py
RESSPyLab/model_minimizer.py
RESSPyLab/modified_cholesky.py
RESSPyLab/mpl_import.py
RESSPyLab/multi_runner.py
RESSPyLab/plot_run_stats.py
RESSPyLab/posdef_check.py
RESSPyLab/reciprocal_barrier.py
RESSPyLab/reduced_cg.py
RESSPyLab/rpl_constraint.py
RESSPyLab/scipy_constr_opt_factory.py
RESSPyLab/scipy_dumper.py
RESSPyLab/solution_vis.py
RESSPyLab/sqp_factory.py
RESSPyLab/sqp_linesearch.py
RESSPyLab/sqp_solver.py
RESSPyLab/sqp_trustregion.py
RESSPyLab/steihaug_col.py
RESSPyLab/summary_tables_maker.py
RESSPyLab/uvc_constraints.py
RESSPyLab/uvc_li_opt_constraints.py
RESSPyLab/uvc_limited_info_opt.py
RESSPyLab/uvc_model.py
RESSPyLab/uvc_parameter_identification.py
RESSPyLab/uvc_plotter.py
RESSPyLab/vc_li_opt_constraints.py
RESSPyLab/vc_limited_info_opt.py
RESSPyLab/vc_parameter_identification.py
RESSPyLab-1.1.6.dist-info/AUTHORS.rst
RESSPyLab-1.1.6.dist-info/LICENSE
RESSPyLab-1.1.6.dist-info/METADATA
RESSPyLab-1.1.6.dist-info/WHEEL
RESSPyLab-1.1.6.dist-info/entry_points.txt
RESSPyLab-1.1.6.dist-info/top_level.txt
RESSPyLab-1.1.6.dist-info/RECORD
