Metadata-Version: 2.1
Name: RESSPyLab
Version: 1.1.6
Summary: Resilient Steel Structures Laboratory (RESSLab) Python Library
Home-page: https://github.com/AlbanoCastroSousa/RESSPyLab
Author: Albano de Castro e Sousa and Alexander R. Hartloper
Author-email: albano.sousa@epfl.ch, alexander.hartloper@epfl.ch
License: MIT license
Keywords: RESSPyLab
Platform: UNKNOWN
Classifier: Development Status :: 2 - Pre-Alpha
Classifier: Intended Audience :: Developers
Classifier: License :: OSI Approved :: MIT License
Classifier: Natural Language :: English
Classifier: Programming Language :: Python :: 2.7
Classifier: Programming Language :: Python :: 3.7
Requires-Dist: Click (>=6.0)
Requires-Dist: numpy (>=1.10.2)
Requires-Dist: pandas
Requires-Dist: algopy
Requires-Dist: numdifftools
Requires-Dist: matplotlib
Requires-Dist: quadprog
Requires-Dist: scipy (>=1.1.0)
